peloterm/__init__.py
peloterm/cli.py
peloterm/config.py
peloterm/controller.py
peloterm/data_processor.py
peloterm/data_recorder.py
peloterm/device_manager.py
peloterm/display.py
peloterm/logo.py
peloterm/monitor.py
peloterm/scanner.py
peloterm/strava_integration.py
peloterm/trainer.py
peloterm/devices/__init__.py
peloterm/devices/base.py
peloterm/devices/ftms_parsers.py
peloterm/devices/heart_rate.py
peloterm/devices/insideride_ftms_parser.py
peloterm/devices/mock.py
peloterm/devices/speed_cadence.py
peloterm/devices/trainer.py
peloterm/tests/__init__.py
peloterm/tests/raw_ftms_data.json
peloterm/tests/test_config.py
peloterm/tests/test_controller.py
peloterm/tests/test_data_recorder.py
peloterm/tests/test_devices.py
peloterm/tests/test_display.py
peloterm/tests/test_ftms_parsers.py
peloterm/tests/test_insideride_parser.py
peloterm/tests/test_mock_data.py
peloterm/tests/test_scanner.py
peloterm/tests/test_web_server.py
peloterm/web/__init__.py
peloterm/web/mock_data.py
peloterm/web/server.py
peloterm/web/static/favicon.ico
peloterm/web/static/index.html
peloterm/web/static/assets/index-CGa3q8LL.css
peloterm/web/static/assets/index-KSWnC6wE.js
peloterm-0.1.4.dist-info/METADATA
peloterm-0.1.4.dist-info/WHEEL
peloterm-0.1.4.dist-info/entry_points.txt
peloterm-0.1.4.dist-info/licenses/LICENSE
peloterm-0.1.4.dist-info/RECORD
